{"format":1,"version":"4.5.2","settings":"bdad5569bfea1c485bea36f0d2092ed6","files":{"section1___init___py":{"hash":"182b2dca469bf063cbcf996d517b03da","index":{"nums":[1,0,0,0,0,0,0],"html_filename":"section1___init___py.html","relative_filename":"section1/__init__.py"}},"section1_cards_py":{"hash":"cf59b52ea83964fa994bb95a8e7462de","index":{"nums":[1,134,0,1,0,0,0],"html_filename":"section1_cards_py.html","relative_filename":"section1/cards.py"}},"section1_fraction_py":{"hash":"4b67d4e4763026d53a89ebff28554c7b","index":{"nums":[1,66,0,0,0,0,0],"html_filename":"section1_fraction_py.html","relative_filename":"section1/fraction.py"}},"section1_logic_gates_py":{"hash":"573440d724ad414c12c4499bb3a68c68","index":{"nums":[1,104,0,3,0,0,0],"html_filename":"section1_logic_gates_py.html","relative_filename":"section1/logic_gates.py"}},"unittest_mock_py":{"hash":"4a9370d0cf74a8509843eeb60d7a1635","index":{"nums":[1,1304,0,1304,0,0,0],"html_filename":"unittest_mock_py.html","relative_filename":"unittest/mock.py"}},"section1_sudoku_py":{"hash":"d60a22fee731b030f335260ba23c68a1","index":{"nums":[1,109,0,4,0,0,0],"html_filename":"section1_sudoku_py.html","relative_filename":"section1/sudoku.py"}},"section1_utils_py":{"hash":"32a071820bf24195854c8932277f4912","index":{"nums":[1,10,0,0,0,0,0],"html_filename":"section1_utils_py.html","relative_filename":"section1/utils.py"}}}}